hello.py
svlearn/__init__.py
svlearn/common/__init__.py
svlearn/common/decorators.py
svlearn/common/log_config.py
svlearn/common/nnio.py
svlearn/common/sv_types.py
svlearn/common/svexception.py
svlearn/common/utils.py
svlearn/config/__init__.py
svlearn/config/configuration.py
svlearn_core-0.1.4.dist-info/METADATA
svlearn_core-0.1.4.dist-info/WHEEL
svlearn_core-0.1.4.dist-info/top_level.txt
svlearn_core-0.1.4.dist-info/RECORD
