Metadata-Version: 2.2
Name: svlearn-core
Version: 0.1.4
Summary: Add your description here
Requires-Python: >=3.12
Requires-Dist: decorator>=5.1.1
Requires-Dist: instructor>=1.7.2
Requires-Dist: ipykernel>=6.29.5
Requires-Dist: ipywidgets>=8.1.5
Requires-Dist: loguru>=0.7.3
Requires-Dist: markdown>=3.7
Requires-Dist: matplotlib>=3.10.0
Requires-Dist: mkdocs>=1.6.1
Requires-Dist: mkdocs-awesome-pages-plugin>=2.10.1
Requires-Dist: mkdocs-include-markdown-plugin>=7.1.2
Requires-Dist: mkdocs-material>=9.5.49
Requires-Dist: mkdocs-material-extensions>=1.3.1
Requires-Dist: mkdocs-mermaid2-plugin>=1.2.1
Requires-Dist: mkdocstrings[python]>=0.27.0
Requires-Dist: mknotebooks>=0.8.0
Requires-Dist: numpy>=2.2.1
Requires-Dist: pandas>=2.2.3
Requires-Dist: pathlib>=1.0.1
Requires-Dist: plotly>=5.24.1
Requires-Dist: pydantic>=2.10.5
Requires-Dist: pykwalify>=1.8.0
Requires-Dist: pytest>=8.3.4
Requires-Dist: python-dotenv>=1.0.1
Requires-Dist: rich>=13.9.4
Requires-Dist: ruamel-yaml>=0.18.10
Requires-Dist: ruff>=0.9.0
Requires-Dist: scikit-learn>=1.6.0
Requires-Dist: seaborn>=0.13.2
